winshotor/__init__.py
winshotor/screenshotor.py
winshotor-0.1.2.dist-info/METADATA
winshotor-0.1.2.dist-info/WHEEL
winshotor-0.1.2.dist-info/top_level.txt
winshotor-0.1.2.dist-info/RECORD
