Metadata-Version: 2.1
Name: winshotor
Version: 0.1.2
Summary: python windows screen snapshot tool.<Windows Only>
Home-page: UNKNOWN
Author: Eagle'sBaby
Author-email: 2229066748@qq.com
Maintainer: Eagle'sBaby
Maintainer-email: 2229066748@qq.com
License: Apache Licence 2.0
Keywords: screenshot,windows
Platform: all
Classifier: Programming Language :: Python
Classifier: Programming Language :: Python :: 3
Requires-Python: >=3
